jefferson_street_singer_ingest/__init__.py
jefferson_street_singer_ingest/services/__init__.py
jefferson_street_singer_ingest/services/entry/__init__.py
jefferson_street_singer_ingest/services/entry/run_command.py
jefferson_street_singer_ingest/services/state/ingest_bookmark.py
jefferson_street_singer_ingest/services/state/state_management.py
jefferson_street_singer_ingest/services/stream/__init__.py
jefferson_street_singer_ingest/services/stream/base_tap_stream.py
jefferson_street_singer_ingest/services/stream/rest_stream.py
jefferson_street_singer_ingest/services/tap/__init__.py
jefferson_street_singer_ingest/services/tap/base_tap.py
jefferson_street_singer_ingest/services/target/__init__.py
jefferson_street_singer_ingest/services/target/avro_generator.py
jefferson_street_singer_ingest/services/target/base_google_cloud_storage_target.py
jefferson_street_singer_ingest-2.13.0.dist-info/METADATA
jefferson_street_singer_ingest-2.13.0.dist-info/WHEEL
jefferson_street_singer_ingest-2.13.0.dist-info/RECORD
