Metadata-Version: 2.1
Name: jefferson-street-singer-ingest
Version: 2.13.0
Summary: Library holding the taps and targets for Jefferson Street Ingestion
Author: Nikolai McFall
Author-email: nikolai@jeffersonst.io
Requires-Python: >=3.8,<3.9
Classifier: Programming Language :: Python :: 3
Classifier: Programming Language :: Python :: 3.8
Requires-Dist: fastavro (>=1.6.1,<2.0.0)
Requires-Dist: google (>=3.0.0,<4.0.0)
Requires-Dist: google-api-python-client (>=2.64.0,<3.0.0)
Requires-Dist: google-cloud-storage (>=2.5.0,<3.0.0)
Requires-Dist: mergedeep (>=1.3.4,<2.0.0)
Requires-Dist: pandas (>=1.4.4,<2.0.0)
Requires-Dist: rec-avro (>=0.0.4,<0.0.5)
Requires-Dist: requests (>=2.28.1,<3.0.0)
Requires-Dist: singer-sdk (==0.1.6)
